cycsound/__init__.py
cycsound/__main__.py
cycsound/_core.cpython-314-darwin.so
cycsound-0.1.0.dist-info/METADATA
cycsound-0.1.0.dist-info/WHEEL
cycsound-0.1.0.dist-info/entry_points.txt
cycsound-0.1.0.dist-info/licenses/LICENSE
cycsound-0.1.0.dist-info/RECORD
