Metadata-Version: 2.4
Name: cycsound
Version: 0.1.0
Summary: Cython bindings for the Csound audio synthesis library
Keywords: audio,csound,cython,music,synthesis,dsp,sound
Author-Email: Shakeeb Alireza <shakfu@users.noreply.github.com>
License-Expression: MIT
Classifier: Development Status :: 3 - Alpha
Classifier: Intended Audience :: Developers
Classifier: Intended Audience :: Science/Research
Classifier: Operating System :: MacOS
Classifier: Operating System :: POSIX :: Linux
Classifier: Operating System :: Microsoft :: Windows
Classifier: Programming Language :: Cython
Classifier: Programming Language :: Python :: 3
Classifier: Programming Language :: Python :: 3.9
Classifier: Programming Language :: Python :: 3.10
Classifier: Programming Language :: Python :: 3.11
Classifier: Programming Language :: Python :: 3.12
Classifier: Programming Language :: Python :: 3.13
Classifier: Programming Language :: Python :: 3.14
Classifier: Topic :: Multimedia :: Sound/Audio
Classifier: Topic :: Multimedia :: Sound/Audio :: Sound Synthesis
Classifier: Topic :: Scientific/Engineering
Project-URL: Homepage, https://github.com/shakfu/cycsound
Project-URL: Repository, https://github.com/shakfu/cycsound
Project-URL: Issues, https://github.com/shakfu/cycsound/issues
Project-URL: Changelog, https://github.com/shakfu/cycsound/blob/main/CHANGELOG.md
Requires-Python: >=3.10
